effidict/__init__.py
effidict/_version.py
effidict/disk_backend.py
effidict/effidict.py
effidict/replacement_strategies.py
effidict-0.1.1.dist-info/licenses/LICENSE
effidict-0.1.1.dist-info/METADATA
effidict-0.1.1.dist-info/WHEEL
effidict-0.1.1.dist-info/top_level.txt
effidict-0.1.1.dist-info/RECORD
